iron/__init__.py
iron/adjbox.py
iron/mc.dll
iron/mc_linux.so
iron/mc_mac.so
iron/phi.dll
iron/phi.py
iron/phi_linux.so
iron/phi_mac.so
iron/sera.py
iron/data/accel_data.csv
iron/data/dfs_fixed.csv
IRonPy-0.3.88.dist-info/LICENSE
IRonPy-0.3.88.dist-info/METADATA
IRonPy-0.3.88.dist-info/WHEEL
IRonPy-0.3.88.dist-info/top_level.txt
IRonPy-0.3.88.dist-info/RECORD
