Metadata-Version: 2.1
Name: IRonPy
Version: 0.3.88
Summary: IRon Package
Home-page: https://github.com/berreergun/IRonPy
Author: berre
Author-email: berreergunn@gmail.com
License: MIT
Platform: UNKNOWN
Requires-Python: >=2
License-File: LICENSE
Requires-Dist: matplotlib
Requires-Dist: numpy
Requires-Dist: pandas
Requires-Dist: sklearn
Requires-Dist: pywin32 (>=1.0) ; platform_system == "Windows"
